tests/conftest.py
tests/test_client.py
wis2downloader/__init__.py
wis2downloader/app.py
wis2downloader/cli.py
wis2downloader/log.py
wis2downloader/metrics.py
wis2downloader/downloader/__init__.py
wis2downloader/queue/__init__.py
wis2downloader/static/openapi.yaml
wis2downloader/subscriber/__init__.py
wis2downloader/templates/swagger.html
wis2downloader/utils/__init__.py
wis2downloader/utils/config.py
wis2downloader/utils/validate_target.py
wis2downloader/utils/validate_topic.py
wis2downloader-0.3.2.dist-info/LICENSE
wis2downloader-0.3.2.dist-info/METADATA
wis2downloader-0.3.2.dist-info/WHEEL
wis2downloader-0.3.2.dist-info/entry_points.txt
wis2downloader-0.3.2.dist-info/top_level.txt
wis2downloader-0.3.2.dist-info/RECORD
