Metadata-Version: 2.1
Name: wis2downloader
Version: 0.3.2
Summary: Python package to manage subscriptions and downloads from the WIS2.0
Author: Rory Burke
Maintainer: Rory Burke
Maintainer-email: "David I. Berry" <dberry@wmo.int>
License:                                  Apache License
Keywords: WIS2.0,MQTT,subscribe,download
Requires-Python: >=3.8
License-File: LICENSE
Requires-Dist: click
Requires-Dist: certifi>=2024.2.2
Requires-Dist: flask>=3.0.3
Requires-Dist: flask-cors>=4.0.0
Requires-Dist: paho-mqtt>=2.0.0
Requires-Dist: prometheus_client>=0.20.0
Requires-Dist: requests
Requires-Dist: urllib3>=2.2.1
Requires-Dist: pywis-topics>=0.3.2
Requires-Dist: pyyaml
